pytorch_tokenizers/__init__.py
pytorch_tokenizers/constants.py
pytorch_tokenizers/hf_tokenizer.py
pytorch_tokenizers/llama2c.py
pytorch_tokenizers/pytorch_tokenizers_cpp.cpython-312-x86_64-linux-gnu.so
pytorch_tokenizers/tiktoken.py
pytorch_tokenizers/include/pytorch/tokenizers/base64.h
pytorch_tokenizers/include/pytorch/tokenizers/bpe_tokenizer_base.h
pytorch_tokenizers/include/pytorch/tokenizers/compiler.h
pytorch_tokenizers/include/pytorch/tokenizers/error.h
pytorch_tokenizers/include/pytorch/tokenizers/hf_tokenizer.h
pytorch_tokenizers/include/pytorch/tokenizers/llama2c_tokenizer.h
pytorch_tokenizers/include/pytorch/tokenizers/log.h
pytorch_tokenizers/include/pytorch/tokenizers/normalizer.h
pytorch_tokenizers/include/pytorch/tokenizers/pcre2_regex.h
pytorch_tokenizers/include/pytorch/tokenizers/pre_tokenizer.h
pytorch_tokenizers/include/pytorch/tokenizers/re2_regex.h
pytorch_tokenizers/include/pytorch/tokenizers/regex.h
pytorch_tokenizers/include/pytorch/tokenizers/result.h
pytorch_tokenizers/include/pytorch/tokenizers/sentencepiece.h
pytorch_tokenizers/include/pytorch/tokenizers/std_regex.h
pytorch_tokenizers/include/pytorch/tokenizers/string_integer_map.h
pytorch_tokenizers/include/pytorch/tokenizers/tekken.h
pytorch_tokenizers/include/pytorch/tokenizers/tiktoken.h
pytorch_tokenizers/include/pytorch/tokenizers/token_decoder.h
pytorch_tokenizers/include/pytorch/tokenizers/tokenizer.h
pytorch_tokenizers/tools/__init__.py
pytorch_tokenizers/tools/llama2c/__init__.py
pytorch_tokenizers/tools/llama2c/convert.py
pytorch_tokenizers-1.0.1.dist-info/METADATA
pytorch_tokenizers-1.0.1.dist-info/WHEEL
pytorch_tokenizers-1.0.1.dist-info/top_level.txt
pytorch_tokenizers-1.0.1.dist-info/RECORD
pytorch_tokenizers-1.0.1.dist-info/licenses/LICENSE
