Metadata-Version: 2.4
Name: pytorch_tokenizers
Version: 1.0.1
Summary: A package with common tokenizers in Python and C++
Home-page: https://github.com/meta-pytorch/tokenizers
Author-email: PyTorch Team <packages@pytorch.org>
License: BSD 3-Clause License
Project-URL: Homepage, https://pytorch.org/executorch/
Project-URL: Repository, https://github.com/pytorch/executorch
Project-URL: Issues, https://github.com/pytorch/executorch/issues
Project-URL: Changelog, https://github.com/pytorch/executorch/releases
Keywords: pytorch,machine learning,llm
Classifier: Development Status :: 4 - Beta
Classifier: Intended Audience :: Developers
Classifier: Intended Audience :: Education
Classifier: Intended Audience :: Science/Research
Classifier: License :: OSI Approved :: BSD License
Classifier: Topic :: Scientific/Engineering
Classifier: Topic :: Scientific/Engineering :: Mathematics
Classifier: Topic :: Scientific/Engineering :: Artificial Intelligence
Classifier: Topic :: Software Development
Classifier: Topic :: Software Development :: Libraries
Classifier: Topic :: Software Development :: Libraries :: Python Modules
Classifier: Programming Language :: C++
Classifier: Programming Language :: Python :: 3
Classifier: Programming Language :: Python :: 3.10
Classifier: Programming Language :: Python :: 3.11
Classifier: Programming Language :: Python :: 3.12
Requires-Python: >=3.10
License-File: LICENSE
Requires-Dist: tiktoken
Requires-Dist: tokenizers
Requires-Dist: sentencepiece
Dynamic: description
Dynamic: description-content-type
Dynamic: home-page
Dynamic: license-file
Dynamic: requires-python
